genecast/__init__.py
genecast/cli.py
genecast/dist.py
genecast/report_generator.py
genecast/snf.py
genecast/visualization.py
genecast/ward.py
genecast/demodata/Actin_test/actin_nuc.fa
genecast-0.1.3.dist-info/licenses/LICENSE
genecast-0.1.3.dist-info/METADATA
genecast-0.1.3.dist-info/WHEEL
genecast-0.1.3.dist-info/entry_points.txt
genecast-0.1.3.dist-info/top_level.txt
genecast-0.1.3.dist-info/RECORD
