Metadata-Version: 2.4
Name: genecast
Version: 0.1.3
Summary: A comprehensive CLI tool for genomic similarity network fusion and analysis.
Author: Genecast Team
License-Expression: MIT
Classifier: Programming Language :: Python :: 3
Classifier: Operating System :: OS Independent
Requires-Python: >=3.11
License-File: LICENSE
Requires-Dist: numpy
Requires-Dist: pandas
Requires-Dist: scipy
Requires-Dist: scikit-learn
Requires-Dist: matplotlib
Requires-Dist: umap-learn
Requires-Dist: pycirclize
Dynamic: license-file
